README.md
setup.cfg
setup.py
LRBench/__init__.py
LRBench/__main__.py
LRBench/utility.py
LRBench.egg-info/PKG-INFO
LRBench.egg-info/SOURCES.txt
LRBench.egg-info/dependency_links.txt
LRBench.egg-info/requires.txt
LRBench.egg-info/top_level.txt
LRBench/database/DBDriver.py
LRBench/database/DBPostgreSQL.py
LRBench/database/__init__.py
LRBench/framework/__init__.py
LRBench/lr/LR.py
LRBench/lr/LRfunctions.py
LRBench/lr/__init__.py
LRBench/lr/piecewiseLR.py
LRBench/monitor/__init__.py