Metadata-Version: 2.1
Name: LRBench
Version: 0.0.0.1
Summary: A learning rate recommending and benchmarking tool.
Home-page: https://github.com/git-disl/LRBench
Author: Yanzhao Wu
Author-email: yanzhaowumail@gmail.com
License: UNKNOWN
Download-URL: https://github.com/git-disl/LRBench/archive/master.zip
Keywords: LEARNING RATE,TRAINING,DEEP LEARNING
Platform: UNKNOWN
Classifier: Development Status :: 3 - Alpha
Classifier: Intended Audience :: Developers
Classifier: Intended Audience :: Science/Research
Classifier: Programming Language :: Python :: 2.7
Classifier: Programming Language :: Python :: 3
Classifier: Programming Language :: Python :: 3.4
Classifier: Programming Language :: Python :: 3.5
Classifier: Programming Language :: Python :: 3.6
